{
  "b37a98d204b2": {
    "href": "/library/llama3-chatqa:latest",
    "name": "llama3-chatqa:latest",
    "input_types": [
      "Text"
    ],
    "updated_str": "1 year ago",
    "context_window": "8K",
    "size_str": "4.7GB"
  },
  "ab8941f03aa3": {
    "href": "/library/llama3-chatqa:70b",
    "name": "llama3-chatqa:70b",
    "input_types": [
      "Text"
    ],
    "updated_str": "1 year ago",
    "context_window": "8K",
    "size_str": "40GB"
  },
  "010674c8ebb4": {
    "href": "/library/llama3-chatqa:8b-v1.5-q2_K",
    "name": "llama3-chatqa:8b-v1.5-q2_K",
    "input_types": [
      "Text"
    ],
    "updated_str": "1 year ago",
    "context_window": "8K",
    "size_str": "3.2GB"
  },
  "6d4cf2ccd7df": {
    "href": "/library/llama3-chatqa:8b-v1.5-q3_K_S",
    "name": "llama3-chatqa:8b-v1.5-q3_K_S",
    "input_types": [
      "Text"
    ],
    "updated_str": "1 year ago",
    "context_window": "8K",
    "size_str": "3.7GB"
  },
  "d1cbce0911ee": {
    "href": "/library/llama3-chatqa:8b-v1.5-q3_K_M",
    "name": "llama3-chatqa:8b-v1.5-q3_K_M",
    "input_types": [
      "Text"
    ],
    "updated_str": "1 year ago",
    "context_window": "8K",
    "size_str": "4.0GB"
  },
  "748c33a3a51f": {
    "href": "/library/llama3-chatqa:8b-v1.5-q3_K_L",
    "name": "llama3-chatqa:8b-v1.5-q3_K_L",
    "input_types": [
      "Text"
    ],
    "updated_str": "1 year ago",
    "context_window": "8K",
    "size_str": "4.3GB"
  },
  "598e30318446": {
    "href": "/library/llama3-chatqa:8b-v1.5-q4_1",
    "name": "llama3-chatqa:8b-v1.5-q4_1",
    "input_types": [
      "Text"
    ],
    "updated_str": "1 year ago",
    "context_window": "8K",
    "size_str": "5.1GB"
  },
  "c4c5c98e11c6": {
    "href": "/library/llama3-chatqa:8b-v1.5-q4_K_S",
    "name": "llama3-chatqa:8b-v1.5-q4_K_S",
    "input_types": [
      "Text"
    ],
    "updated_str": "1 year ago",
    "context_window": "8K",
    "size_str": "4.7GB"
  },
  "07e385a3991b": {
    "href": "/library/llama3-chatqa:8b-v1.5-q4_K_M",
    "name": "llama3-chatqa:8b-v1.5-q4_K_M",
    "input_types": [
      "Text"
    ],
    "updated_str": "1 year ago",
    "context_window": "8K",
    "size_str": "4.9GB"
  },
  "7775bf791816": {
    "href": "/library/llama3-chatqa:8b-v1.5-q5_0",
    "name": "llama3-chatqa:8b-v1.5-q5_0",
    "input_types": [
      "Text"
    ],
    "updated_str": "1 year ago",
    "context_window": "8K",
    "size_str": "5.6GB"
  },
  "233019c7a259": {
    "href": "/library/llama3-chatqa:8b-v1.5-q5_1",
    "name": "llama3-chatqa:8b-v1.5-q5_1",
    "input_types": [
      "Text"
    ],
    "updated_str": "1 year ago",
    "context_window": "8K",
    "size_str": "6.1GB"
  },
  "3eab2a2fa684": {
    "href": "/library/llama3-chatqa:8b-v1.5-q5_K_S",
    "name": "llama3-chatqa:8b-v1.5-q5_K_S",
    "input_types": [
      "Text"
    ],
    "updated_str": "1 year ago",
    "context_window": "8K",
    "size_str": "5.6GB"
  },
  "d0e9675cf775": {
    "href": "/library/llama3-chatqa:8b-v1.5-q5_K_M",
    "name": "llama3-chatqa:8b-v1.5-q5_K_M",
    "input_types": [
      "Text"
    ],
    "updated_str": "1 year ago",
    "context_window": "8K",
    "size_str": "5.7GB"
  },
  "576770c27967": {
    "href": "/library/llama3-chatqa:8b-v1.5-q6_K",
    "name": "llama3-chatqa:8b-v1.5-q6_K",
    "input_types": [
      "Text"
    ],
    "updated_str": "1 year ago",
    "context_window": "8K",
    "size_str": "6.6GB"
  },
  "4b48f929dc16": {
    "href": "/library/llama3-chatqa:8b-v1.5-q8_0",
    "name": "llama3-chatqa:8b-v1.5-q8_0",
    "input_types": [
      "Text"
    ],
    "updated_str": "1 year ago",
    "context_window": "8K",
    "size_str": "8.5GB"
  },
  "54f366e1115a": {
    "href": "/library/llama3-chatqa:8b-v1.5-fp16",
    "name": "llama3-chatqa:8b-v1.5-fp16",
    "input_types": [
      "Text"
    ],
    "updated_str": "1 year ago",
    "context_window": "8K",
    "size_str": "16GB"
  },
  "8fde9769839c": {
    "href": "/library/llama3-chatqa:70b-v1.5-q2_K",
    "name": "llama3-chatqa:70b-v1.5-q2_K",
    "input_types": [
      "Text"
    ],
    "updated_str": "1 year ago",
    "context_window": "8K",
    "size_str": "26GB"
  },
  "6c487abb0e1f": {
    "href": "/library/llama3-chatqa:70b-v1.5-q3_K_S",
    "name": "llama3-chatqa:70b-v1.5-q3_K_S",
    "input_types": [
      "Text"
    ],
    "updated_str": "1 year ago",
    "context_window": "8K",
    "size_str": "31GB"
  },
  "47d621963e0c": {
    "href": "/library/llama3-chatqa:70b-v1.5-q3_K_M",
    "name": "llama3-chatqa:70b-v1.5-q3_K_M",
    "input_types": [
      "Text"
    ],
    "updated_str": "1 year ago",
    "context_window": "8K",
    "size_str": "34GB"
  },
  "d894d5e58d1e": {
    "href": "/library/llama3-chatqa:70b-v1.5-q3_K_L",
    "name": "llama3-chatqa:70b-v1.5-q3_K_L",
    "input_types": [
      "Text"
    ],
    "updated_str": "1 year ago",
    "context_window": "8K",
    "size_str": "37GB"
  },
  "ae356afdf521": {
    "href": "/library/llama3-chatqa:70b-v1.5-q4_1",
    "name": "llama3-chatqa:70b-v1.5-q4_1",
    "input_types": [
      "Text"
    ],
    "updated_str": "1 year ago",
    "context_window": "8K",
    "size_str": "44GB"
  },
  "7d6f62f9c1c6": {
    "href": "/library/llama3-chatqa:70b-v1.5-q4_K_S",
    "name": "llama3-chatqa:70b-v1.5-q4_K_S",
    "input_types": [
      "Text"
    ],
    "updated_str": "1 year ago",
    "context_window": "8K",
    "size_str": "40GB"
  },
  "bd9cc94a71c9": {
    "href": "/library/llama3-chatqa:70b-v1.5-q4_K_M",
    "name": "llama3-chatqa:70b-v1.5-q4_K_M",
    "input_types": [
      "Text"
    ],
    "updated_str": "1 year ago",
    "context_window": "8K",
    "size_str": "43GB"
  },
  "29f1075baf3a": {
    "href": "/library/llama3-chatqa:70b-v1.5-q5_0",
    "name": "llama3-chatqa:70b-v1.5-q5_0",
    "input_types": [
      "Text"
    ],
    "updated_str": "1 year ago",
    "context_window": "8K",
    "size_str": "49GB"
  },
  "3adf827c2f0c": {
    "href": "/library/llama3-chatqa:70b-v1.5-q5_1",
    "name": "llama3-chatqa:70b-v1.5-q5_1",
    "input_types": [
      "Text"
    ],
    "updated_str": "1 year ago",
    "context_window": "8K",
    "size_str": "53GB"
  },
  "2650a0fefd9b": {
    "href": "/library/llama3-chatqa:70b-v1.5-q5_K_S",
    "name": "llama3-chatqa:70b-v1.5-q5_K_S",
    "input_types": [
      "Text"
    ],
    "updated_str": "1 year ago",
    "context_window": "8K",
    "size_str": "49GB"
  },
  "275a26d672ac": {
    "href": "/library/llama3-chatqa:70b-v1.5-q5_K_M",
    "name": "llama3-chatqa:70b-v1.5-q5_K_M",
    "input_types": [
      "Text"
    ],
    "updated_str": "1 year ago",
    "context_window": "8K",
    "size_str": "50GB"
  },
  "8cc009d2a270": {
    "href": "/library/llama3-chatqa:70b-v1.5-q6_K",
    "name": "llama3-chatqa:70b-v1.5-q6_K",
    "input_types": [
      "Text"
    ],
    "updated_str": "1 year ago",
    "context_window": "8K",
    "size_str": "58GB"
  },
  "1fb999cb1cad": {
    "href": "/library/llama3-chatqa:70b-v1.5-q8_0",
    "name": "llama3-chatqa:70b-v1.5-q8_0",
    "input_types": [
      "Text"
    ],
    "updated_str": "1 year ago",
    "context_window": "8K",
    "size_str": "75GB"
  },
  "d46dd05cde4c": {
    "href": "/library/llama3-chatqa:70b-v1.5-fp16",
    "name": "llama3-chatqa:70b-v1.5-fp16",
    "input_types": [
      "Text"
    ],
    "updated_str": "1 year ago",
    "context_window": "8K",
    "size_str": "141GB"
  }
}