{
  "36211dad2b15": {
    "href": "/library/llama3-groq-tool-use:latest",
    "name": "llama3-groq-tool-use:latest",
    "input_types": [
      "Text"
    ],
    "updated_str": "1 year ago",
    "context_window": "4.7GB",
    "size_str": "8K"
  },
  "696d50e6fc55": {
    "href": "/library/llama3-groq-tool-use:70b",
    "name": "llama3-groq-tool-use:70b",
    "input_types": [
      "Text"
    ],
    "updated_str": "1 year ago",
    "context_window": "40GB",
    "size_str": "8K"
  },
  "37fac70005b1": {
    "href": "/library/llama3-groq-tool-use:8b-q2_K",
    "name": "llama3-groq-tool-use:8b-q2_K",
    "input_types": [
      "Text"
    ],
    "updated_str": "1 year ago",
    "context_window": "3.2GB",
    "size_str": "8K"
  },
  "3f7165ed6ac3": {
    "href": "/library/llama3-groq-tool-use:8b-q3_K_S",
    "name": "llama3-groq-tool-use:8b-q3_K_S",
    "input_types": [
      "Text"
    ],
    "updated_str": "1 year ago",
    "context_window": "3.7GB",
    "size_str": "8K"
  },
  "def359e8ef42": {
    "href": "/library/llama3-groq-tool-use:8b-q3_K_M",
    "name": "llama3-groq-tool-use:8b-q3_K_M",
    "input_types": [
      "Text"
    ],
    "updated_str": "1 year ago",
    "context_window": "4.0GB",
    "size_str": "8K"
  },
  "57fbbf9656ef": {
    "href": "/library/llama3-groq-tool-use:8b-q3_K_L",
    "name": "llama3-groq-tool-use:8b-q3_K_L",
    "input_types": [
      "Text"
    ],
    "updated_str": "1 year ago",
    "context_window": "4.3GB",
    "size_str": "8K"
  },
  "b927899ecb62": {
    "href": "/library/llama3-groq-tool-use:8b-q4_1",
    "name": "llama3-groq-tool-use:8b-q4_1",
    "input_types": [
      "Text"
    ],
    "updated_str": "1 year ago",
    "context_window": "5.1GB",
    "size_str": "8K"
  },
  "9dc66563ded8": {
    "href": "/library/llama3-groq-tool-use:8b-q4_K_S",
    "name": "llama3-groq-tool-use:8b-q4_K_S",
    "input_types": [
      "Text"
    ],
    "updated_str": "1 year ago",
    "context_window": "4.7GB",
    "size_str": "8K"
  },
  "5fa325bad307": {
    "href": "/library/llama3-groq-tool-use:8b-q4_K_M",
    "name": "llama3-groq-tool-use:8b-q4_K_M",
    "input_types": [
      "Text"
    ],
    "updated_str": "1 year ago",
    "context_window": "4.9GB",
    "size_str": "8K"
  },
  "0482e45a0517": {
    "href": "/library/llama3-groq-tool-use:8b-q5_0",
    "name": "llama3-groq-tool-use:8b-q5_0",
    "input_types": [
      "Text"
    ],
    "updated_str": "1 year ago",
    "context_window": "5.6GB",
    "size_str": "8K"
  },
  "45984ff6d001": {
    "href": "/library/llama3-groq-tool-use:8b-q5_1",
    "name": "llama3-groq-tool-use:8b-q5_1",
    "input_types": [
      "Text"
    ],
    "updated_str": "1 year ago",
    "context_window": "6.1GB",
    "size_str": "8K"
  },
  "6a1775abde02": {
    "href": "/library/llama3-groq-tool-use:8b-q5_K_S",
    "name": "llama3-groq-tool-use:8b-q5_K_S",
    "input_types": [
      "Text"
    ],
    "updated_str": "1 year ago",
    "context_window": "5.6GB",
    "size_str": "8K"
  },
  "50c9c554ddd4": {
    "href": "/library/llama3-groq-tool-use:8b-q5_K_M",
    "name": "llama3-groq-tool-use:8b-q5_K_M",
    "input_types": [
      "Text"
    ],
    "updated_str": "1 year ago",
    "context_window": "5.7GB",
    "size_str": "8K"
  },
  "7ec6fd768fe0": {
    "href": "/library/llama3-groq-tool-use:8b-q6_K",
    "name": "llama3-groq-tool-use:8b-q6_K",
    "input_types": [
      "Text"
    ],
    "updated_str": "1 year ago",
    "context_window": "6.6GB",
    "size_str": "8K"
  },
  "58ab12b11127": {
    "href": "/library/llama3-groq-tool-use:8b-q8_0",
    "name": "llama3-groq-tool-use:8b-q8_0",
    "input_types": [
      "Text"
    ],
    "updated_str": "1 year ago",
    "context_window": "8.5GB",
    "size_str": "8K"
  },
  "be9b2c0775a5": {
    "href": "/library/llama3-groq-tool-use:8b-fp16",
    "name": "llama3-groq-tool-use:8b-fp16",
    "input_types": [
      "Text"
    ],
    "updated_str": "1 year ago",
    "context_window": "16GB",
    "size_str": "8K"
  },
  "dab8a158f092": {
    "href": "/library/llama3-groq-tool-use:70b-q2_K",
    "name": "llama3-groq-tool-use:70b-q2_K",
    "input_types": [
      "Text"
    ],
    "updated_str": "1 year ago",
    "context_window": "26GB",
    "size_str": "8K"
  },
  "4f446f9b1b86": {
    "href": "/library/llama3-groq-tool-use:70b-q3_K_S",
    "name": "llama3-groq-tool-use:70b-q3_K_S",
    "input_types": [
      "Text"
    ],
    "updated_str": "1 year ago",
    "context_window": "31GB",
    "size_str": "8K"
  },
  "5e0c9286cabe": {
    "href": "/library/llama3-groq-tool-use:70b-q3_K_M",
    "name": "llama3-groq-tool-use:70b-q3_K_M",
    "input_types": [
      "Text"
    ],
    "updated_str": "1 year ago",
    "context_window": "34GB",
    "size_str": "8K"
  },
  "94b979ce931c": {
    "href": "/library/llama3-groq-tool-use:70b-q3_K_L",
    "name": "llama3-groq-tool-use:70b-q3_K_L",
    "input_types": [
      "Text"
    ],
    "updated_str": "1 year ago",
    "context_window": "37GB",
    "size_str": "8K"
  },
  "35972e96c25d": {
    "href": "/library/llama3-groq-tool-use:70b-q4_1",
    "name": "llama3-groq-tool-use:70b-q4_1",
    "input_types": [
      "Text"
    ],
    "updated_str": "1 year ago",
    "context_window": "44GB",
    "size_str": "8K"
  },
  "464bc22f0c7f": {
    "href": "/library/llama3-groq-tool-use:70b-q4_K_S",
    "name": "llama3-groq-tool-use:70b-q4_K_S",
    "input_types": [
      "Text"
    ],
    "updated_str": "1 year ago",
    "context_window": "40GB",
    "size_str": "8K"
  },
  "45eafa1bfbd8": {
    "href": "/library/llama3-groq-tool-use:70b-q4_K_M",
    "name": "llama3-groq-tool-use:70b-q4_K_M",
    "input_types": [
      "Text"
    ],
    "updated_str": "1 year ago",
    "context_window": "43GB",
    "size_str": "8K"
  },
  "5c52fd8e4ba7": {
    "href": "/library/llama3-groq-tool-use:70b-q5_0",
    "name": "llama3-groq-tool-use:70b-q5_0",
    "input_types": [
      "Text"
    ],
    "updated_str": "1 year ago",
    "context_window": "49GB",
    "size_str": "8K"
  },
  "337622a2615e": {
    "href": "/library/llama3-groq-tool-use:70b-q5_1",
    "name": "llama3-groq-tool-use:70b-q5_1",
    "input_types": [
      "Text"
    ],
    "updated_str": "1 year ago",
    "context_window": "53GB",
    "size_str": "8K"
  },
  "88450a6c4bc7": {
    "href": "/library/llama3-groq-tool-use:70b-q5_K_S",
    "name": "llama3-groq-tool-use:70b-q5_K_S",
    "input_types": [
      "Text"
    ],
    "updated_str": "1 year ago",
    "context_window": "49GB",
    "size_str": "8K"
  },
  "7e1f34171905": {
    "href": "/library/llama3-groq-tool-use:70b-q5_K_M",
    "name": "llama3-groq-tool-use:70b-q5_K_M",
    "input_types": [
      "Text"
    ],
    "updated_str": "1 year ago",
    "context_window": "50GB",
    "size_str": "8K"
  },
  "fe241542dd2b": {
    "href": "/library/llama3-groq-tool-use:70b-q6_K",
    "name": "llama3-groq-tool-use:70b-q6_K",
    "input_types": [
      "Text"
    ],
    "updated_str": "1 year ago",
    "context_window": "58GB",
    "size_str": "8K"
  },
  "e998a1023200": {
    "href": "/library/llama3-groq-tool-use:70b-q8_0",
    "name": "llama3-groq-tool-use:70b-q8_0",
    "input_types": [
      "Text"
    ],
    "updated_str": "1 year ago",
    "context_window": "75GB",
    "size_str": "8K"
  },
  "8ef2a1906612": {
    "href": "/library/llama3-groq-tool-use:70b-fp16",
    "name": "llama3-groq-tool-use:70b-fp16",
    "input_types": [
      "Text"
    ],
    "updated_str": "1 year ago",
    "context_window": "141GB",
    "size_str": "8K"
  }
}