{
  "483a8282af74": {
    "href": "/library/nexusraven:latest",
    "name": "nexusraven:latest",
    "input_types": [
      "Text"
    ],
    "updated_str": "1 year ago",
    "context_window": "7.4GB",
    "size_str": "16K"
  },
  "335cee44ee6e": {
    "href": "/library/nexusraven:13b-v2-q2_K",
    "name": "nexusraven:13b-v2-q2_K",
    "input_types": [
      "Text"
    ],
    "updated_str": "1 year ago",
    "context_window": "5.4GB",
    "size_str": "16K"
  },
  "e05ddc03a204": {
    "href": "/library/nexusraven:13b-v2-q3_K_S",
    "name": "nexusraven:13b-v2-q3_K_S",
    "input_types": [
      "Text"
    ],
    "updated_str": "1 year ago",
    "context_window": "5.7GB",
    "size_str": "16K"
  },
  "9c3abc556fee": {
    "href": "/library/nexusraven:13b-v2-q3_K_M",
    "name": "nexusraven:13b-v2-q3_K_M",
    "input_types": [
      "Text"
    ],
    "updated_str": "1 year ago",
    "context_window": "6.3GB",
    "size_str": "16K"
  },
  "030244bdb058": {
    "href": "/library/nexusraven:13b-v2-q3_K_L",
    "name": "nexusraven:13b-v2-q3_K_L",
    "input_types": [
      "Text"
    ],
    "updated_str": "1 year ago",
    "context_window": "6.9GB",
    "size_str": "16K"
  },
  "9d97f7422b57": {
    "href": "/library/nexusraven:13b-v2-q4_1",
    "name": "nexusraven:13b-v2-q4_1",
    "input_types": [
      "Text"
    ],
    "updated_str": "1 year ago",
    "context_window": "8.2GB",
    "size_str": "16K"
  },
  "d922b5f359d4": {
    "href": "/library/nexusraven:13b-v2-q4_K_S",
    "name": "nexusraven:13b-v2-q4_K_S",
    "input_types": [
      "Text"
    ],
    "updated_str": "1 year ago",
    "context_window": "7.4GB",
    "size_str": "16K"
  },
  "c686cfb91b9b": {
    "href": "/library/nexusraven:13b-v2-q4_K_M",
    "name": "nexusraven:13b-v2-q4_K_M",
    "input_types": [
      "Text"
    ],
    "updated_str": "1 year ago",
    "context_window": "7.9GB",
    "size_str": "16K"
  },
  "93d134582405": {
    "href": "/library/nexusraven:13b-v2-q5_0",
    "name": "nexusraven:13b-v2-q5_0",
    "input_types": [
      "Text"
    ],
    "updated_str": "1 year ago",
    "context_window": "9.0GB",
    "size_str": "16K"
  },
  "223215c51cfb": {
    "href": "/library/nexusraven:13b-v2-q5_1",
    "name": "nexusraven:13b-v2-q5_1",
    "input_types": [
      "Text"
    ],
    "updated_str": "1 year ago",
    "context_window": "9.8GB",
    "size_str": "16K"
  },
  "506b8b5250ba": {
    "href": "/library/nexusraven:13b-v2-q5_K_S",
    "name": "nexusraven:13b-v2-q5_K_S",
    "input_types": [
      "Text"
    ],
    "updated_str": "1 year ago",
    "context_window": "9.0GB",
    "size_str": "16K"
  },
  "8754f5363618": {
    "href": "/library/nexusraven:13b-v2-q5_K_M",
    "name": "nexusraven:13b-v2-q5_K_M",
    "input_types": [
      "Text"
    ],
    "updated_str": "1 year ago",
    "context_window": "9.2GB",
    "size_str": "16K"
  },
  "d81ebb5a6f93": {
    "href": "/library/nexusraven:13b-v2-q6_K",
    "name": "nexusraven:13b-v2-q6_K",
    "input_types": [
      "Text"
    ],
    "updated_str": "1 year ago",
    "context_window": "11GB",
    "size_str": "16K"
  },
  "2f770812d079": {
    "href": "/library/nexusraven:13b-v2-q8_0",
    "name": "nexusraven:13b-v2-q8_0",
    "input_types": [
      "Text"
    ],
    "updated_str": "1 year ago",
    "context_window": "14GB",
    "size_str": "16K"
  },
  "6e9f4b4dff57": {
    "href": "/library/nexusraven:13b-v2-fp16",
    "name": "nexusraven:13b-v2-fp16",
    "input_types": [
      "Text"
    ],
    "updated_str": "1 year ago",
    "context_window": "26GB",
    "size_str": "16K"
  },
  "88af7c885f6d": {
    "href": "/library/nexusraven:13b-q2_K",
    "name": "nexusraven:13b-q2_K",
    "input_types": [
      "Text"
    ],
    "updated_str": "1 year ago",
    "context_window": "5.4GB",
    "size_str": "16K"
  },
  "c327bf4400c3": {
    "href": "/library/nexusraven:13b-q3_K_S",
    "name": "nexusraven:13b-q3_K_S",
    "input_types": [
      "Text"
    ],
    "updated_str": "1 year ago",
    "context_window": "5.7GB",
    "size_str": "16K"
  },
  "32ee186898d8": {
    "href": "/library/nexusraven:13b-q3_K_M",
    "name": "nexusraven:13b-q3_K_M",
    "input_types": [
      "Text"
    ],
    "updated_str": "1 year ago",
    "context_window": "6.3GB",
    "size_str": "16K"
  },
  "be1c4d4ebf80": {
    "href": "/library/nexusraven:13b-q3_K_L",
    "name": "nexusraven:13b-q3_K_L",
    "input_types": [
      "Text"
    ],
    "updated_str": "1 year ago",
    "context_window": "6.9GB",
    "size_str": "16K"
  },
  "336957c1d527": {
    "href": "/library/nexusraven:13b-q4_0",
    "name": "nexusraven:13b-q4_0",
    "input_types": [
      "Text"
    ],
    "updated_str": "1 year ago",
    "context_window": "7.4GB",
    "size_str": "16K"
  },
  "cc0185e939a9": {
    "href": "/library/nexusraven:13b-q4_1",
    "name": "nexusraven:13b-q4_1",
    "input_types": [
      "Text"
    ],
    "updated_str": "1 year ago",
    "context_window": "8.2GB",
    "size_str": "16K"
  },
  "01ab3a1e2bd0": {
    "href": "/library/nexusraven:13b-q4_K_S",
    "name": "nexusraven:13b-q4_K_S",
    "input_types": [
      "Text"
    ],
    "updated_str": "1 year ago",
    "context_window": "7.4GB",
    "size_str": "16K"
  },
  "869ecaf32849": {
    "href": "/library/nexusraven:13b-q4_K_M",
    "name": "nexusraven:13b-q4_K_M",
    "input_types": [
      "Text"
    ],
    "updated_str": "1 year ago",
    "context_window": "7.9GB",
    "size_str": "16K"
  },
  "1edef32ba6b0": {
    "href": "/library/nexusraven:13b-q5_0",
    "name": "nexusraven:13b-q5_0",
    "input_types": [
      "Text"
    ],
    "updated_str": "1 year ago",
    "context_window": "9.0GB",
    "size_str": "16K"
  },
  "5695d35736eb": {
    "href": "/library/nexusraven:13b-q5_1",
    "name": "nexusraven:13b-q5_1",
    "input_types": [
      "Text"
    ],
    "updated_str": "1 year ago",
    "context_window": "9.8GB",
    "size_str": "16K"
  },
  "d47e757e2f8a": {
    "href": "/library/nexusraven:13b-q5_K_S",
    "name": "nexusraven:13b-q5_K_S",
    "input_types": [
      "Text"
    ],
    "updated_str": "1 year ago",
    "context_window": "9.0GB",
    "size_str": "16K"
  },
  "3ba5150eacb6": {
    "href": "/library/nexusraven:13b-q5_K_M",
    "name": "nexusraven:13b-q5_K_M",
    "input_types": [
      "Text"
    ],
    "updated_str": "1 year ago",
    "context_window": "9.2GB",
    "size_str": "16K"
  },
  "fa629e4e0d35": {
    "href": "/library/nexusraven:13b-q6_K",
    "name": "nexusraven:13b-q6_K",
    "input_types": [
      "Text"
    ],
    "updated_str": "1 year ago",
    "context_window": "11GB",
    "size_str": "16K"
  },
  "25fba36ef0af": {
    "href": "/library/nexusraven:13b-q8_0",
    "name": "nexusraven:13b-q8_0",
    "input_types": [
      "Text"
    ],
    "updated_str": "1 year ago",
    "context_window": "14GB",
    "size_str": "16K"
  },
  "038c3ee38ca3": {
    "href": "/library/nexusraven:13b-fp16",
    "name": "nexusraven:13b-fp16",
    "input_types": [
      "Text"
    ],
    "updated_str": "1 year ago",
    "context_window": "26GB",
    "size_str": "16K"
  }
}